{
  "components": [
    {
      "type": "content",
      "container": "main",
      "components": [
        {
          "type": "row",
          "components": [
            {
              "type": "col",
              "class": "col-md-12",
              "components": [
                {
                  "type": "template-form",
                  "name": "form0",
                  "components": [
                    {
                      "type": "row",
                      "style": {
                        "marginBottom": "1rem"
                      },
                      "components": [
                        {
                          "type": "col",
                          "class": "col-md-3",
                          "components": [
                            {
                              "type": "label",
                              "text": "Category Name",
                              "component": "CategoryName",
                              "name": "CategoryNameLabel",
                              "style": {
                                "width": "100%"
                              }
                            }
                          ]
                        },
                        {
                          "type": "col",
                          "class": "col-md-9",
                          "components": [
                            {
                              "maxLength": 50,
                              "type": "textbox",
                              "name": "CategoryName",
                              "style": {
                                "display": "block",
                                "width": "100%"
                              }
                            },
                            {
                              "type": "required-validator",
                              "name": "CategoryNameRequiredValidator",
                              "component": "CategoryName",
                              "text": "CategoryName is required",
                              "style": {
                                "position": "absolute"
                              }
                            }
                          ]
                        }
                      ]
                    },
                    {
                      "type": "row",
                      "components": [
                        {
                          "type": "col",
                          "class": "col offset-sm-3",
                          "components": [
                            {
                              "type": "button",
                              "buttonType": "submit",
                              "icon": "save",
                              "text": "Save",
                              "buttonStyle": "primary"
                            },
                            {
                              "type": "button",
                              "buttonStyle": "light",
                              "style": {
                                "marginLeft": "1rem"
                              },
                              "text": "Cancel",
                              "events": {
                                "click": [
                                  {
                                    "type": "back"
                                  }
                                ]
                              }
                            }
                          ]
                        }
                      ]
                    }
                  ],
                  "events": {
                    "submit": [
                      {
                        "error": [
                          {
                            "detail": "Unable to create new Category!",
                            "severity": "error",
                            "summary": "Error",
                            "type": "notify"
                          }
                        ],
                        "name": "ConData.createCategory",
                        "parameters": [
                          {
                            "name": "Category",
                            "value": "${event}"
                          }
                        ],
                        "then": [
                          {
                            "type": "back"
                          }
                        ],
                        "type": "invoke"
                      }
                    ]
                  }
                }
              ]
            }
          ]
        }
      ]
    }
  ],
  "events": {
    "load": []
  },
  "name": "Add Category",
  "layout": "Main",
  "access": [
    "SuperAdmin"
  ]
}